{
    "province": "湖北省",
    "prov_code": "42",
    "city": "武汉市",
    "city_code": "4201",
    "districts": [
        {
            "_id": "5c18605e2722b75024b9d7a3",
            "code": "420117",
            "district": "新洲区",
            "subdistricts": [
                {
                    "_id": "5c18605e2722b75024b9d7b2",
                    "code": "420117001",
                    "subdistrict": "邾城街道办事处"
                },
                {
                    "_id": "5c18605e2722b75024b9d7b1",
                    "code": "420117002",
                    "subdistrict": "阳逻街道办事处"
                },
                {
                    "_id": "5c18605e2722b75024b9d7b0",
                    "code": "420117003",
                    "subdistrict": "仓埠街道办事处"
                },
                {
                    "_id": "5c18605e2722b75024b9d7af",
                    "code": "420117004",
                    "subdistrict": "汪集街道办事处"
                },
                {
                    "_id": "5c18605e2722b75024b9d7ae",
                    "code": "420117005",
                    "subdistrict": "李集街道办事处"
                },
                {
                    "_id": "5c18605e2722b75024b9d7ad",
                    "code": "420117006",
                    "subdistrict": "三店街道办事处"
                },
                {
                    "_id": "5c18605e2722b75024b9d7ac",
                    "code": "420117007",
                    "subdistrict": "潘塘街道办事处"
                },
                {
                    "_id": "5c18605e2722b75024b9d7ab",
                    "code": "420117008",
                    "subdistrict": "旧街街道办事处"
                },
                {
                    "_id": "5c18605e2722b75024b9d7aa",
                    "code": "420117009",
                    "subdistrict": "双柳街道办事处"
                },
                {
                    "_id": "5c18605e2722b75024b9d7a9",
                    "code": "420117010",
                    "subdistrict": "涨渡湖街道办事处"
                },
                {
                    "_id": "5c18605e2722b75024b9d7a8",
                    "code": "420117011",
                    "subdistrict": "辛冲街道办事处"
                },
                {
                    "_id": "5c18605e2722b75024b9d7a7",
                    "code": "420117012",
                    "subdistrict": "徐古街道办事处"
                },
                {
                    "_id": "5c18605e2722b75024b9d7a6",
                    "code": "420117102",
                    "subdistrict": "凤凰镇"
                },
                {
                    "_id": "5c18605e2722b75024b9d7a5",
                    "code": "420117400",
                    "subdistrict": "道观河风景旅游管理处"
                },
                {
                    "_id": "5c18605e2722b75024b9d7a4",
                    "code": "420117406",
                    "subdistrict": "新洲原种场"
                }
            ]
        },
        {
            "_id": "5c18605e2722b75024b9d791",
            "code": "420102",
            "district": "江岸区",
            "subdistricts": [
                {
                    "_id": "5c18605e2722b75024b9d7a2",
                    "code": "420102002",
                    "subdistrict": "大智街办事处"
                },
                {
                    "_id": "5c18605e2722b75024b9d7a1",
                    "code": "420102003",
                    "subdistrict": "一元街办事处"
                },
                {
                    "_id": "5c18605e2722b75024b9d7a0",
                    "code": "420102004",
                    "subdistrict": "车站街办事处"
                },
                {
                    "_id": "5c18605e2722b75024b9d79f",
                    "code": "420102005",
                    "subdistrict": "四唯街办事处"
                },
                {
                    "_id": "5c18605e2722b75024b9d79e",
                    "code": "420102006",
                    "subdistrict": "永清街办事处"
                },
                {
                    "_id": "5c18605e2722b75024b9d79d",
                    "code": "420102007",
                    "subdistrict": "西马街办事处"
                },
                {
                    "_id": "5c18605e2722b75024b9d79c",
                    "code": "420102008",
                    "subdistrict": "球场街办事处"
                },
                {
                    "_id": "5c18605e2722b75024b9d79b",
                    "code": "420102009",
                    "subdistrict": "劳动街办事处"
                },
                {
                    "_id": "5c18605e2722b75024b9d79a",
                    "code": "420102010",
                    "subdistrict": "二七街办事处"
                },
                {
                    "_id": "5c18605e2722b75024b9d799",
                    "code": "420102011",
                    "subdistrict": "新村街办事处"
                },
                {
                    "_id": "5c18605e2722b75024b9d798",
                    "code": "420102012",
                    "subdistrict": "丹水池街办事处"
                },
                {
                    "_id": "5c18605e2722b75024b9d797",
                    "code": "420102014",
                    "subdistrict": "台北街办事处"
                },
                {
                    "_id": "5c18605e2722b75024b9d796",
                    "code": "420102015",
                    "subdistrict": "花桥街办事处"
                },
                {
                    "_id": "5c18605e2722b75024b9d795",
                    "code": "420102016",
                    "subdistrict": "谌家矶街办事处"
                },
                {
                    "_id": "5c18605e2722b75024b9d794",
                    "code": "420102017",
                    "subdistrict": "后湖街办事处"
                },
                {
                    "_id": "5c18605e2722b75024b9d793",
                    "code": "420102018",
                    "subdistrict": "塔子湖街办事处"
                },
                {
                    "_id": "5c18605e2722b75024b9d792",
                    "code": "420102400",
                    "subdistrict": "百步亭花园"
                }
            ]
        },
        {
            "_id": "5c18605e2722b75024b9d781",
            "code": "420103",
            "district": "江汉区",
            "subdistricts": [
                {
                    "_id": "5c18605e2722b75024b9d790",
                    "code": "420103001",
                    "subdistrict": "民族街办事处"
                },
                {
                    "_id": "5c18605e2722b75024b9d78f",
                    "code": "420103002",
                    "subdistrict": "花楼街办事处"
                },
                {
                    "_id": "5c18605e2722b75024b9d78e",
                    "code": "420103003",
                    "subdistrict": "水塔街办事处"
                },
                {
                    "_id": "5c18605e2722b75024b9d78d",
                    "code": "420103004",
                    "subdistrict": "民权街办事处"
                },
                {
                    "_id": "5c18605e2722b75024b9d78c",
                    "code": "420103005",
                    "subdistrict": "满春街办事处"
                },
                {
                    "_id": "5c18605e2722b75024b9d78b",
                    "code": "420103006",
                    "subdistrict": "民意街办事处"
                },
                {
                    "_id": "5c18605e2722b75024b9d78a",
                    "code": "420103007",
                    "subdistrict": "新华街办事处"
                },
                {
                    "_id": "5c18605e2722b75024b9d789",
                    "code": "420103008",
                    "subdistrict": "万松街办事处"
                },
                {
                    "_id": "5c18605e2722b75024b9d788",
                    "code": "420103009",
                    "subdistrict": "唐家墩街办事处"
                },
                {
                    "_id": "5c18605e2722b75024b9d787",
                    "code": "420103010",
                    "subdistrict": "北湖街办事处"
                },
                {
                    "_id": "5c18605e2722b75024b9d786",
                    "code": "420103011",
                    "subdistrict": "前进街办事处"
                },
                {
                    "_id": "5c18605e2722b75024b9d785",
                    "code": "420103012",
                    "subdistrict": "常青街办事处"
                },
                {
                    "_id": "5c18605e2722b75024b9d784",
                    "code": "420103013",
                    "subdistrict": "汉兴街办事处"
                },
                {
                    "_id": "5c18605e2722b75024b9d783",
                    "code": "420103400",
                    "subdistrict": "江汉经济开发区"
                },
                {
                    "_id": "5c18605e2722b75024b9d782",
                    "code": "420103401",
                    "subdistrict": "武汉中央商务区管理委员会"
                }
            ]
        },
        {
            "_id": "5c18605e2722b75024b9d775",
            "code": "420104",
            "district": "硚口区",
            "subdistricts": [
                {
                    "_id": "5c18605e2722b75024b9d780",
                    "code": "420104001",
                    "subdistrict": "古田街道办事处"
                },
                {
                    "_id": "5c18605e2722b75024b9d77f",
                    "code": "420104002",
                    "subdistrict": "韩家墩街道办事处"
                },
                {
                    "_id": "5c18605e2722b75024b9d77e",
                    "code": "420104003",
                    "subdistrict": "宗关街道办事处"
                },
                {
                    "_id": "5c18605e2722b75024b9d77d",
                    "code": "420104004",
                    "subdistrict": "汉水桥街道办事处"
                },
                {
                    "_id": "5c18605e2722b75024b9d77c",
                    "code": "420104005",
                    "subdistrict": "宝丰街道办事处"
                },
                {
                    "_id": "5c18605e2722b75024b9d77b",
                    "code": "420104006",
                    "subdistrict": "荣华街道办事处"
                },
                {
                    "_id": "5c18605e2722b75024b9d77a",
                    "code": "420104008",
                    "subdistrict": "汉中街道办事处"
                },
                {
                    "_id": "5c18605e2722b75024b9d779",
                    "code": "420104009",
                    "subdistrict": "汉正街道办事处"
                },
                {
                    "_id": "5c18605e2722b75024b9d778",
                    "code": "420104010",
                    "subdistrict": "六角亭街道办事处"
                },
                {
                    "_id": "5c18605e2722b75024b9d777",
                    "code": "420104011",
                    "subdistrict": "长丰街道办事处"
                },
                {
                    "_id": "5c18605e2722b75024b9d776",
                    "code": "420104012",
                    "subdistrict": "易家街道办事处"
                }
            ]
        },
        {
            "_id": "5c18605e2722b75024b9d769",
            "code": "420105",
            "district": "汉阳区",
            "subdistricts": [
                {
                    "_id": "5c18605e2722b75024b9d774",
                    "code": "420105002",
                    "subdistrict": "建桥街办事处"
                },
                {
                    "_id": "5c18605e2722b75024b9d773",
                    "code": "420105004",
                    "subdistrict": "晴川街办事处"
                },
                {
                    "_id": "5c18605e2722b75024b9d772",
                    "code": "420105005",
                    "subdistrict": "鹦鹉街办事处"
                },
                {
                    "_id": "5c18605e2722b75024b9d771",
                    "code": "420105006",
                    "subdistrict": "洲头街办事处"
                },
                {
                    "_id": "5c18605e2722b75024b9d770",
                    "code": "420105007",
                    "subdistrict": "五里墩街办事处"
                },
                {
                    "_id": "5c18605e2722b75024b9d76f",
                    "code": "420105008",
                    "subdistrict": "琴断口街办事处"
                },
                {
                    "_id": "5c18605e2722b75024b9d76e",
                    "code": "420105009",
                    "subdistrict": "江汉二桥街办事处"
                },
                {
                    "_id": "5c18605e2722b75024b9d76d",
                    "code": "420105010",
                    "subdistrict": "永丰街办事处"
                },
                {
                    "_id": "5c18605e2722b75024b9d76c",
                    "code": "420105011",
                    "subdistrict": "江堤街办事处"
                },
                {
                    "_id": "5c18605e2722b75024b9d76b",
                    "code": "420105012",
                    "subdistrict": "四新街办事处"
                },
                {
                    "_id": "5c18605e2722b75024b9d76a",
                    "code": "420105013",
                    "subdistrict": "龙阳街办事处"
                }
            ]
        },
        {
            "_id": "5c18605e2722b75024b9d759",
            "code": "420106",
            "district": "武昌区",
            "subdistricts": [
                {
                    "_id": "5c18605e2722b75024b9d768",
                    "code": "420106001",
                    "subdistrict": "积玉桥街办事处"
                },
                {
                    "_id": "5c18605e2722b75024b9d767",
                    "code": "420106002",
                    "subdistrict": "杨园街办事处"
                },
                {
                    "_id": "5c18605e2722b75024b9d766",
                    "code": "420106003",
                    "subdistrict": "徐家棚街办事处"
                },
                {
                    "_id": "5c18605e2722b75024b9d765",
                    "code": "420106005",
                    "subdistrict": "粮道街办事处"
                },
                {
                    "_id": "5c18605e2722b75024b9d764",
                    "code": "420106006",
                    "subdistrict": "中华路街办事处"
                },
                {
                    "_id": "5c18605e2722b75024b9d763",
                    "code": "420106007",
                    "subdistrict": "黄鹤楼街办事处"
                },
                {
                    "_id": "5c18605e2722b75024b9d762",
                    "code": "420106008",
                    "subdistrict": "紫阳街办事处"
                },
                {
                    "_id": "5c18605e2722b75024b9d761",
                    "code": "420106009",
                    "subdistrict": "白沙洲街办事处"
                },
                {
                    "_id": "5c18605e2722b75024b9d760",
                    "code": "420106010",
                    "subdistrict": "首义路街办事处"
                },
                {
                    "_id": "5c18605e2722b75024b9d75f",
                    "code": "420106011",
                    "subdistrict": "中南路街办事处"
                },
                {
                    "_id": "5c18605e2722b75024b9d75e",
                    "code": "420106012",
                    "subdistrict": "水果湖街办事处"
                },
                {
                    "_id": "5c18605e2722b75024b9d75d",
                    "code": "420106013",
                    "subdistrict": "珞珈山街办事处"
                },
                {
                    "_id": "5c18605e2722b75024b9d75c",
                    "code": "420106014",
                    "subdistrict": "石洞街办事处"
                },
                {
                    "_id": "5c18605e2722b75024b9d75b",
                    "code": "420106015",
                    "subdistrict": "南湖街办事处"
                },
                {
                    "_id": "5c18605e2722b75024b9d75a",
                    "code": "420106490",
                    "subdistrict": "东湖风景区街道（武昌）"
                }
            ]
        },
        {
            "_id": "5c18605e2722b75024b9d747",
            "code": "420107",
            "district": "青山区",
            "subdistricts": [
                {
                    "_id": "5c18605e2722b75024b9d758",
                    "code": "420107001",
                    "subdistrict": "红卫路街道办事处"
                },
                {
                    "_id": "5c18605e2722b75024b9d757",
                    "code": "420107002",
                    "subdistrict": "冶金街道办事处"
                },
                {
                    "_id": "5c18605e2722b75024b9d756",
                    "code": "420107003",
                    "subdistrict": "新沟桥街道办事处"
                },
                {
                    "_id": "5c18605e2722b75024b9d755",
                    "code": "420107004",
                    "subdistrict": "红钢城街道办事处"
                },
                {
                    "_id": "5c18605e2722b75024b9d754",
                    "code": "420107005",
                    "subdistrict": "工人村街道办事处"
                },
                {
                    "_id": "5c18605e2722b75024b9d753",
                    "code": "420107006",
                    "subdistrict": "青山镇街道办事处"
                },
                {
                    "_id": "5c18605e2722b75024b9d752",
                    "code": "420107007",
                    "subdistrict": "厂前街道办事处"
                },
                {
                    "_id": "5c18605e2722b75024b9d751",
                    "code": "420107008",
                    "subdistrict": "武东街道办事处"
                },
                {
                    "_id": "5c18605e2722b75024b9d750",
                    "code": "420107009",
                    "subdistrict": "白玉山街道办事处"
                },
                {
                    "_id": "5c18605e2722b75024b9d74f",
                    "code": "420107010",
                    "subdistrict": "钢花村街道办事处"
                },
                {
                    "_id": "5c18605e2722b75024b9d74e",
                    "code": "420107400",
                    "subdistrict": "武钢集团公司"
                },
                {
                    "_id": "5c18605e2722b75024b9d74d",
                    "code": "420107401",
                    "subdistrict": "中国一冶有限责任公司"
                },
                {
                    "_id": "5c18605e2722b75024b9d74c",
                    "code": "420107402",
                    "subdistrict": "武钢实业公司"
                },
                {
                    "_id": "5c18605e2722b75024b9d74b",
                    "code": "420107403",
                    "subdistrict": "中国一冶集体企业管理处"
                },
                {
                    "_id": "5c18605e2722b75024b9d74a",
                    "code": "420107404",
                    "subdistrict": "开发区"
                },
                {
                    "_id": "5c18605e2722b75024b9d749",
                    "code": "420107405",
                    "subdistrict": "钢都花园管理委员会"
                },
                {
                    "_id": "5c18605e2722b75024b9d748",
                    "code": "420107406",
                    "subdistrict": "北湖工业园管理办公室"
                }
            ]
        },
        {
            "_id": "5c18605e2722b75024b9d735",
            "code": "420111",
            "district": "洪山区",
            "subdistricts": [
                {
                    "_id": "5c18605e2722b75024b9d746",
                    "code": "420111001",
                    "subdistrict": "珞南街道"
                },
                {
                    "_id": "5c18605e2722b75024b9d745",
                    "code": "420111002",
                    "subdistrict": "关山街道"
                },
                {
                    "_id": "5c18605e2722b75024b9d744",
                    "code": "420111003",
                    "subdistrict": "狮子山街道"
                },
                {
                    "_id": "5c18605e2722b75024b9d743",
                    "code": "420111004",
                    "subdistrict": "张家湾街道"
                },
                {
                    "_id": "5c18605e2722b75024b9d742",
                    "code": "420111005",
                    "subdistrict": "梨园街道"
                },
                {
                    "_id": "5c18605e2722b75024b9d741",
                    "code": "420111006",
                    "subdistrict": "卓刀泉街道"
                },
                {
                    "_id": "5c18605e2722b75024b9d740",
                    "code": "420111007",
                    "subdistrict": "洪山街道办事处"
                },
                {
                    "_id": "5c18605e2722b75024b9d73f",
                    "code": "420111008",
                    "subdistrict": "和平街道办事处"
                },
                {
                    "_id": "5c18605e2722b75024b9d73e",
                    "code": "420111009",
                    "subdistrict": "青菱街道"
                },
                {
                    "_id": "5c18605e2722b75024b9d73d",
                    "code": "420111061",
                    "subdistrict": "八吉府街办事处"
                },
                {
                    "_id": "5c18605e2722b75024b9d73c",
                    "code": "420111080",
                    "subdistrict": "关东街道办事处"
                },
                {
                    "_id": "5c18605e2722b75024b9d73b",
                    "code": "420111081",
                    "subdistrict": "花山街道办事处"
                },
                {
                    "_id": "5c18605e2722b75024b9d73a",
                    "code": "420111082",
                    "subdistrict": "左岭街道办事处"
                },
                {
                    "_id": "5c18605e2722b75024b9d739",
                    "code": "420111083",
                    "subdistrict": "九峰街道办事处"
                },
                {
                    "_id": "5c18605e2722b75024b9d738",
                    "code": "420111205",
                    "subdistrict": "天兴乡"
                },
                {
                    "_id": "5c18605e2722b75024b9d737",
                    "code": "420111460",
                    "subdistrict": "清谭湖办事处"
                },
                {
                    "_id": "5c18605e2722b75024b9d736",
                    "code": "420111491",
                    "subdistrict": "东湖风景区街道（洪山）"
                }
            ]
        },
        {
            "_id": "5c18605e2722b75024b9d723",
            "code": "420112",
            "district": "东西湖区",
            "subdistricts": [
                {
                    "_id": "5c18605e2722b75024b9d734",
                    "code": "420112001",
                    "subdistrict": "吴家山街道办事处"
                },
                {
                    "_id": "5c18605e2722b75024b9d733",
                    "code": "420112002",
                    "subdistrict": "柏泉办事处街道"
                },
                {
                    "_id": "5c18605e2722b75024b9d732",
                    "code": "420112004",
                    "subdistrict": "将军路街道办事处"
                },
                {
                    "_id": "5c18605e2722b75024b9d731",
                    "code": "420112005",
                    "subdistrict": "慈惠街道办事处"
                },
                {
                    "_id": "5c18605e2722b75024b9d730",
                    "code": "420112006",
                    "subdistrict": "走马岭街道办事处"
                },
                {
                    "_id": "5c18605e2722b75024b9d72f",
                    "code": "420112007",
                    "subdistrict": "径河街道办事处"
                },
                {
                    "_id": "5c18605e2722b75024b9d72e",
                    "code": "420112008",
                    "subdistrict": "长青街道办事处"
                },
                {
                    "_id": "5c18605e2722b75024b9d72d",
                    "code": "420112011",
                    "subdistrict": "辛安渡办事处街道"
                },
                {
                    "_id": "5c18605e2722b75024b9d72c",
                    "code": "420112012",
                    "subdistrict": "东山办事处街道"
                },
                {
                    "_id": "5c18605e2722b75024b9d72b",
                    "code": "420112013",
                    "subdistrict": "常青花园新区街道管理委员会"
                },
                {
                    "_id": "5c18605e2722b75024b9d72a",
                    "code": "420112014",
                    "subdistrict": "新沟镇街道办事处"
                },
                {
                    "_id": "5c18605e2722b75024b9d729",
                    "code": "420112015",
                    "subdistrict": "金银湖街道办事处"
                },
                {
                    "_id": "5c18605e2722b75024b9d728",
                    "code": "420112400",
                    "subdistrict": "产业管理处"
                },
                {
                    "_id": "5c18605e2722b75024b9d727",
                    "code": "420112401",
                    "subdistrict": "保税物流管理处"
                },
                {
                    "_id": "5c18605e2722b75024b9d726",
                    "code": "420112402",
                    "subdistrict": "海峡两岸科技产业管理处"
                },
                {
                    "_id": "5c18605e2722b75024b9d725",
                    "code": "420112403",
                    "subdistrict": "食品工业管理处"
                },
                {
                    "_id": "5c18605e2722b75024b9d724",
                    "code": "420112404",
                    "subdistrict": "临空经济管理处"
                }
            ]
        },
        {
            "_id": "5c18605e2722b75024b9d71e",
            "code": "420113",
            "district": "汉南区",
            "subdistricts": [
                {
                    "_id": "5c18605e2722b75024b9d722",
                    "code": "420113001",
                    "subdistrict": "纱帽街道办事处"
                },
                {
                    "_id": "5c18605e2722b75024b9d721",
                    "code": "420113002",
                    "subdistrict": "邓南街道办事处"
                },
                {
                    "_id": "5c18605e2722b75024b9d720",
                    "code": "420113003",
                    "subdistrict": "东荆街道办事处"
                },
                {
                    "_id": "5c18605e2722b75024b9d71f",
                    "code": "420113004",
                    "subdistrict": "湘口街道办事处"
                }
            ]
        },
        {
            "_id": "5c18605e2722b75024b9d70d",
            "code": "420114",
            "district": "蔡甸区",
            "subdistricts": [
                {
                    "_id": "5c18605e2722b75024b9d71d",
                    "code": "420114001",
                    "subdistrict": "蔡甸街道办事处"
                },
                {
                    "_id": "5c18605e2722b75024b9d71c",
                    "code": "420114002",
                    "subdistrict": "奓山街道办事处"
                },
                {
                    "_id": "5c18605e2722b75024b9d71b",
                    "code": "420114003",
                    "subdistrict": "永安街道办事处"
                },
                {
                    "_id": "5c18605e2722b75024b9d71a",
                    "code": "420114004",
                    "subdistrict": "侏儒山街道办事处"
                },
                {
                    "_id": "5c18605e2722b75024b9d719",
                    "code": "420114005",
                    "subdistrict": "大集街道办事处"
                },
                {
                    "_id": "5c18605e2722b75024b9d718",
                    "code": "420114006",
                    "subdistrict": "张湾街道办事处"
                },
                {
                    "_id": "5c18605e2722b75024b9d717",
                    "code": "420114070",
                    "subdistrict": "沌口街办事处"
                },
                {
                    "_id": "5c18605e2722b75024b9d716",
                    "code": "420114071",
                    "subdistrict": "军山街道"
                },
                {
                    "_id": "5c18605e2722b75024b9d715",
                    "code": "420114072",
                    "subdistrict": "沌阳街道办事处"
                },
                {
                    "_id": "5c18605e2722b75024b9d714",
                    "code": "420114100",
                    "subdistrict": "索河镇"
                },
                {
                    "_id": "5c18605e2722b75024b9d713",
                    "code": "420114101",
                    "subdistrict": "玉贤镇"
                },
                {
                    "_id": "5c18605e2722b75024b9d712",
                    "code": "420114200",
                    "subdistrict": "消泗乡"
                },
                {
                    "_id": "5c18605e2722b75024b9d711",
                    "code": "420114400",
                    "subdistrict": "桐湖办事处"
                },
                {
                    "_id": "5c18605e2722b75024b9d710",
                    "code": "420114401",
                    "subdistrict": "洪北管委会"
                },
                {
                    "_id": "5c18605e2722b75024b9d70f",
                    "code": "420114405",
                    "subdistrict": "蔡甸经济开发区凤凰山事处"
                },
                {
                    "_id": "5c18605e2722b75024b9d70e",
                    "code": "420114407",
                    "subdistrict": "武汉蔡甸经济发开区管理委员会"
                }
            ]
        },
        {
            "_id": "5c18605e2722b75024b9d6f9",
            "code": "420115",
            "district": "江夏区",
            "subdistricts": [
                {
                    "_id": "5c18605e2722b75024b9d70c",
                    "code": "420115001",
                    "subdistrict": "纸坊街道"
                },
                {
                    "_id": "5c18605e2722b75024b9d70b",
                    "code": "420115002",
                    "subdistrict": "金口街道"
                },
                {
                    "_id": "5c18605e2722b75024b9d70a",
                    "code": "420115003",
                    "subdistrict": "乌龙泉街道"
                },
                {
                    "_id": "5c18605e2722b75024b9d709",
                    "code": "420115005",
                    "subdistrict": "郑店街道"
                },
                {
                    "_id": "5c18605e2722b75024b9d708",
                    "code": "420115007",
                    "subdistrict": "五里界街道"
                },
                {
                    "_id": "5c18605e2722b75024b9d707",
                    "code": "420115008",
                    "subdistrict": "金水办事处"
                },
                {
                    "_id": "5c18605e2722b75024b9d706",
                    "code": "420115009",
                    "subdistrict": "安山街道办事处"
                },
                {
                    "_id": "5c18605e2722b75024b9d705",
                    "code": "420115010",
                    "subdistrict": "山坡街道办事处"
                },
                {
                    "_id": "5c18605e2722b75024b9d704",
                    "code": "420115014",
                    "subdistrict": "法泗街道"
                },
                {
                    "_id": "5c18605e2722b75024b9d703",
                    "code": "420115015",
                    "subdistrict": "湖泗街道"
                },
                {
                    "_id": "5c18605e2722b75024b9d702",
                    "code": "420115016",
                    "subdistrict": "舒安街道办事处"
                },
                {
                    "_id": "5c18605e2722b75024b9d701",
                    "code": "420115086",
                    "subdistrict": "佛祖岭街道办事处"
                },
                {
                    "_id": "5c18605e2722b75024b9d700",
                    "code": "420115087",
                    "subdistrict": "豹澥街道办事处"
                },
                {
                    "_id": "5c18605e2722b75024b9d6ff",
                    "code": "420115088",
                    "subdistrict": "流芳街道"
                },
                {
                    "_id": "5c18605e2722b75024b9d6fe",
                    "code": "420115089",
                    "subdistrict": "滨湖街道办事处"
                },
                {
                    "_id": "5c18605e2722b75024b9d6fd",
                    "code": "420115401",
                    "subdistrict": "江夏区经济开发区庙山办事处"
                },
                {
                    "_id": "5c18605e2722b75024b9d6fc",
                    "code": "420115402",
                    "subdistrict": "江夏区经济开发区藏龙岛办事处"
                },
                {
                    "_id": "5c18605e2722b75024b9d6fb",
                    "code": "420115403",
                    "subdistrict": "江夏区经济开发区大桥新区办事处"
                },
                {
                    "_id": "5c18605e2722b75024b9d6fa",
                    "code": "420115405",
                    "subdistrict": "金港新区办事处"
                }
            ]
        },
        {
            "_id": "5c18605e2722b75024b9d6e4",
            "code": "420116",
            "district": "黄陂区",
            "subdistricts": [
                {
                    "_id": "5c18605e2722b75024b9d6f8",
                    "code": "420116001",
                    "subdistrict": "前川街道"
                },
                {
                    "_id": "5c18605e2722b75024b9d6f7",
                    "code": "420116002",
                    "subdistrict": "祁家湾街道"
                },
                {
                    "_id": "5c18605e2722b75024b9d6f6",
                    "code": "420116003",
                    "subdistrict": "横店街道"
                },
                {
                    "_id": "5c18605e2722b75024b9d6f5",
                    "code": "420116004",
                    "subdistrict": "罗汉寺街道"
                },
                {
                    "_id": "5c18605e2722b75024b9d6f4",
                    "code": "420116005",
                    "subdistrict": "滠口街道"
                },
                {
                    "_id": "5c18605e2722b75024b9d6f3",
                    "code": "420116006",
                    "subdistrict": "六指街道"
                },
                {
                    "_id": "5c18605e2722b75024b9d6f2",
                    "code": "420116007",
                    "subdistrict": "天河街道"
                },
                {
                    "_id": "5c18605e2722b75024b9d6f1",
                    "code": "420116008",
                    "subdistrict": "王家河街道"
                },
                {
                    "_id": "5c18605e2722b75024b9d6f0",
                    "code": "420116009",
                    "subdistrict": "长轩岭街道"
                },
                {
                    "_id": "5c18605e2722b75024b9d6ef",
                    "code": "420116010",
                    "subdistrict": "李集街道"
                },
                {
                    "_id": "5c18605e2722b75024b9d6ee",
                    "code": "420116011",
                    "subdistrict": "姚集街道"
                },
                {
                    "_id": "5c18605e2722b75024b9d6ed",
                    "code": "420116012",
                    "subdistrict": "蔡榨街道"
                },
                {
                    "_id": "5c18605e2722b75024b9d6ec",
                    "code": "420116013",
                    "subdistrict": "武湖街道"
                },
                {
                    "_id": "5c18605e2722b75024b9d6eb",
                    "code": "420116014",
                    "subdistrict": "三里桥街道办事处"
                },
                {
                    "_id": "5c18605e2722b75024b9d6ea",
                    "code": "420116015",
                    "subdistrict": "蔡店街道办事处"
                },
                {
                    "_id": "5c18605e2722b75024b9d6e9",
                    "code": "420116201",
                    "subdistrict": "木兰乡"
                },
                {
                    "_id": "5c18605e2722b75024b9d6e8",
                    "code": "420116401",
                    "subdistrict": "木兰山风景区管理处"
                },
                {
                    "_id": "5c18605e2722b75024b9d6e7",
                    "code": "420116402",
                    "subdistrict": "大潭办事处"
                },
                {
                    "_id": "5c18605e2722b75024b9d6e6",
                    "code": "420116403",
                    "subdistrict": "盘龙城经济开发区"
                },
                {
                    "_id": "5c18605e2722b75024b9d6e5",
                    "code": "420116404",
                    "subdistrict": "汉口北商贸物流枢纽区管委会"
                }
            ]
        }
    ],
    "id": 180
}