{
    "province": "辽宁省",
    "prov_code": "21",
    "city": "鞍山市",
    "city_code": "2103",
    "districts": [
        {
            "_id": "5c1860582722b75024b99485",
            "code": "210381",
            "district": "海城市",
            "subdistricts": [
                {
                    "_id": "5c1860582722b75024b994a0",
                    "code": "210381001",
                    "subdistrict": "海州街道办事处"
                },
                {
                    "_id": "5c1860582722b75024b9949f",
                    "code": "210381002",
                    "subdistrict": "兴海街道办事处"
                },
                {
                    "_id": "5c1860582722b75024b9949e",
                    "code": "210381003",
                    "subdistrict": "响堂街道办事处"
                },
                {
                    "_id": "5c1860582722b75024b9949d",
                    "code": "210381004",
                    "subdistrict": "东四街道办事处"
                },
                {
                    "_id": "5c1860582722b75024b9949c",
                    "code": "210381005",
                    "subdistrict": "验军街道办事处"
                },
                {
                    "_id": "5c1860582722b75024b9949b",
                    "code": "210381006",
                    "subdistrict": "温泉街道办事处"
                },
                {
                    "_id": "5c1860582722b75024b9949a",
                    "code": "210381101",
                    "subdistrict": "孤山镇"
                },
                {
                    "_id": "5c1860582722b75024b99499",
                    "code": "210381102",
                    "subdistrict": "岔沟镇"
                },
                {
                    "_id": "5c1860582722b75024b99498",
                    "code": "210381103",
                    "subdistrict": "接文镇"
                },
                {
                    "_id": "5c1860582722b75024b99497",
                    "code": "210381104",
                    "subdistrict": "析木镇"
                },
                {
                    "_id": "5c1860582722b75024b99496",
                    "code": "210381105",
                    "subdistrict": "马风镇"
                },
                {
                    "_id": "5c1860582722b75024b99495",
                    "code": "210381107",
                    "subdistrict": "牌楼镇"
                },
                {
                    "_id": "5c1860582722b75024b99494",
                    "code": "210381108",
                    "subdistrict": "八里镇"
                },
                {
                    "_id": "5c1860582722b75024b99493",
                    "code": "210381109",
                    "subdistrict": "毛祁镇"
                },
                {
                    "_id": "5c1860582722b75024b99492",
                    "code": "210381110",
                    "subdistrict": "英落镇"
                },
                {
                    "_id": "5c1860582722b75024b99491",
                    "code": "210381111",
                    "subdistrict": "感王镇"
                },
                {
                    "_id": "5c1860582722b75024b99490",
                    "code": "210381112",
                    "subdistrict": "西柳镇"
                },
                {
                    "_id": "5c1860582722b75024b9948f",
                    "code": "210381113",
                    "subdistrict": "中小镇"
                },
                {
                    "_id": "5c1860582722b75024b9948e",
                    "code": "210381114",
                    "subdistrict": "王石镇"
                },
                {
                    "_id": "5c1860582722b75024b9948d",
                    "code": "210381115",
                    "subdistrict": "南台镇"
                },
                {
                    "_id": "5c1860582722b75024b9948c",
                    "code": "210381118",
                    "subdistrict": "腾鳌镇"
                },
                {
                    "_id": "5c1860582722b75024b9948b",
                    "code": "210381121",
                    "subdistrict": "耿庄镇"
                },
                {
                    "_id": "5c1860582722b75024b9948a",
                    "code": "210381123",
                    "subdistrict": "牛庄镇"
                },
                {
                    "_id": "5c1860582722b75024b99489",
                    "code": "210381124",
                    "subdistrict": "西四镇"
                },
                {
                    "_id": "5c1860582722b75024b99488",
                    "code": "210381125",
                    "subdistrict": "望台镇"
                },
                {
                    "_id": "5c1860582722b75024b99487",
                    "code": "210381126",
                    "subdistrict": "温香镇"
                },
                {
                    "_id": "5c1860582722b75024b99486",
                    "code": "210381127",
                    "subdistrict": "高坨镇"
                }
            ]
        },
        {
            "_id": "5c1860582722b75024b99473",
            "code": "210302",
            "district": "铁东区",
            "subdistricts": [
                {
                    "_id": "5c1860582722b75024b99484",
                    "code": "210302001",
                    "subdistrict": "长甸街道办事处"
                },
                {
                    "_id": "5c1860582722b75024b99483",
                    "code": "210302002",
                    "subdistrict": "解放街道办事处"
                },
                {
                    "_id": "5c1860582722b75024b99482",
                    "code": "210302003",
                    "subdistrict": "山南街道办事处"
                },
                {
                    "_id": "5c1860582722b75024b99481",
                    "code": "210302004",
                    "subdistrict": "园林街道办事处"
                },
                {
                    "_id": "5c1860582722b75024b99480",
                    "code": "210302005",
                    "subdistrict": "胜利街道办事处"
                },
                {
                    "_id": "5c1860582722b75024b9947f",
                    "code": "210302006",
                    "subdistrict": "站前街道办事处"
                },
                {
                    "_id": "5c1860582722b75024b9947e",
                    "code": "210302007",
                    "subdistrict": "钢城街道办事处"
                },
                {
                    "_id": "5c1860582722b75024b9947d",
                    "code": "210302008",
                    "subdistrict": "和平街道办事处"
                },
                {
                    "_id": "5c1860582722b75024b9947c",
                    "code": "210302009",
                    "subdistrict": "对炉街道办事处"
                },
                {
                    "_id": "5c1860582722b75024b9947b",
                    "code": "210302010",
                    "subdistrict": "东长甸街道办事处"
                },
                {
                    "_id": "5c1860582722b75024b9947a",
                    "code": "210302011",
                    "subdistrict": "湖南街道办事处"
                },
                {
                    "_id": "5c1860582722b75024b99479",
                    "code": "210302012",
                    "subdistrict": "常青街道办事处"
                },
                {
                    "_id": "5c1860582722b75024b99478",
                    "code": "210302013",
                    "subdistrict": "新兴街道办事处"
                },
                {
                    "_id": "5c1860582722b75024b99477",
                    "code": "210302014",
                    "subdistrict": "旧堡街道办事处"
                },
                {
                    "_id": "5c1860582722b75024b99476",
                    "code": "210302015",
                    "subdistrict": "大孤山街道"
                },
                {
                    "_id": "5c1860582722b75024b99475",
                    "code": "210302016",
                    "subdistrict": "温泉街道办事处"
                },
                {
                    "_id": "5c1860582722b75024b99474",
                    "code": "210302400",
                    "subdistrict": "玉佛山风景区管理委员会"
                }
            ]
        },
        {
            "_id": "5c1860582722b75024b99464",
            "code": "210303",
            "district": "铁西区",
            "subdistricts": [
                {
                    "_id": "5c1860582722b75024b99472",
                    "code": "210303001",
                    "subdistrict": "启明街道办事处"
                },
                {
                    "_id": "5c1860582722b75024b99471",
                    "code": "210303002",
                    "subdistrict": "繁荣街道办事处"
                },
                {
                    "_id": "5c1860582722b75024b99470",
                    "code": "210303003",
                    "subdistrict": "八家子街道办事处"
                },
                {
                    "_id": "5c1860582722b75024b9946f",
                    "code": "210303004",
                    "subdistrict": "兴盛街道办事处"
                },
                {
                    "_id": "5c1860582722b75024b9946e",
                    "code": "210303005",
                    "subdistrict": "共和街道办事处"
                },
                {
                    "_id": "5c1860582722b75024b9946d",
                    "code": "210303006",
                    "subdistrict": "永乐街道办事处"
                },
                {
                    "_id": "5c1860582722b75024b9946c",
                    "code": "210303007",
                    "subdistrict": "北陶官街道办事处"
                },
                {
                    "_id": "5c1860582722b75024b9946b",
                    "code": "210303008",
                    "subdistrict": "南华街道办事处"
                },
                {
                    "_id": "5c1860582722b75024b9946a",
                    "code": "210303009",
                    "subdistrict": "大陆街道办事处"
                },
                {
                    "_id": "5c1860582722b75024b99469",
                    "code": "210303010",
                    "subdistrict": "新陶官街道办事处"
                },
                {
                    "_id": "5c1860582722b75024b99468",
                    "code": "210303011",
                    "subdistrict": "新城街道办事处"
                },
                {
                    "_id": "5c1860582722b75024b99467",
                    "code": "210303012",
                    "subdistrict": "永发街道办事处"
                },
                {
                    "_id": "5c1860582722b75024b99466",
                    "code": "210303013",
                    "subdistrict": "宁远街道办事处"
                },
                {
                    "_id": "5c1860582722b75024b99465",
                    "code": "210303014",
                    "subdistrict": "达道湾街道办事处"
                }
            ]
        },
        {
            "_id": "5c1860582722b75024b99456",
            "code": "210304",
            "district": "立山区",
            "subdistricts": [
                {
                    "_id": "5c1860582722b75024b99463",
                    "code": "210304001",
                    "subdistrict": "友好街道办事处"
                },
                {
                    "_id": "5c1860582722b75024b99462",
                    "code": "210304004",
                    "subdistrict": "双山街道办事处"
                },
                {
                    "_id": "5c1860582722b75024b99461",
                    "code": "210304006",
                    "subdistrict": "立山街道办事处"
                },
                {
                    "_id": "5c1860582722b75024b99460",
                    "code": "210304008",
                    "subdistrict": "曙光街道办事处"
                },
                {
                    "_id": "5c1860582722b75024b9945f",
                    "code": "210304009",
                    "subdistrict": "灵山街道办事处"
                },
                {
                    "_id": "5c1860582722b75024b9945e",
                    "code": "210304013",
                    "subdistrict": "深南街道办事处"
                },
                {
                    "_id": "5c1860582722b75024b9945d",
                    "code": "210304014",
                    "subdistrict": "深北街道办事处"
                },
                {
                    "_id": "5c1860582722b75024b9945c",
                    "code": "210304015",
                    "subdistrict": "沙河街道办事处"
                },
                {
                    "_id": "5c1860582722b75024b9945b",
                    "code": "210304016",
                    "subdistrict": "滨河街道办事处"
                },
                {
                    "_id": "5c1860582722b75024b9945a",
                    "code": "210304017",
                    "subdistrict": "千山街道办事处"
                },
                {
                    "_id": "5c1860582722b75024b99459",
                    "code": "210304019",
                    "subdistrict": "齐大山街道办事处"
                },
                {
                    "_id": "5c1860582722b75024b99458",
                    "code": "210304020",
                    "subdistrict": "汪峪街道办事处"
                },
                {
                    "_id": "5c1860582722b75024b99457",
                    "code": "210304021",
                    "subdistrict": "红岭街道办事处"
                }
            ]
        },
        {
            "_id": "5c1860582722b75024b9944f",
            "code": "210311",
            "district": "千山区",
            "subdistricts": [
                {
                    "_id": "5c1860582722b75024b99455",
                    "code": "210311005",
                    "subdistrict": "对桩石街道办事处"
                },
                {
                    "_id": "5c1860582722b75024b99454",
                    "code": "210311006",
                    "subdistrict": "汤岗子街道办事处"
                },
                {
                    "_id": "5c1860582722b75024b99453",
                    "code": "210311007",
                    "subdistrict": "东鞍山街道办事处"
                },
                {
                    "_id": "5c1860582722b75024b99452",
                    "code": "210311102",
                    "subdistrict": "唐家房镇"
                },
                {
                    "_id": "5c1860582722b75024b99451",
                    "code": "210311103",
                    "subdistrict": "大屯镇"
                },
                {
                    "_id": "5c1860582722b75024b99450",
                    "code": "210311104",
                    "subdistrict": "甘泉镇"
                }
            ]
        },
        {
            "_id": "5c1860582722b75024b9943d",
            "code": "210321",
            "district": "台安县",
            "subdistricts": [
                {
                    "_id": "5c1860582722b75024b9944e",
                    "code": "210321001",
                    "subdistrict": "八角台街道办事处"
                },
                {
                    "_id": "5c1860582722b75024b9944d",
                    "code": "210321002",
                    "subdistrict": "台东街道办事处"
                },
                {
                    "_id": "5c1860582722b75024b9944c",
                    "code": "210321003",
                    "subdistrict": "台南街道办事处"
                },
                {
                    "_id": "5c1860582722b75024b9944b",
                    "code": "210321004",
                    "subdistrict": "台北街道办事处"
                },
                {
                    "_id": "5c1860582722b75024b9944a",
                    "code": "210321101",
                    "subdistrict": "西佛镇"
                },
                {
                    "_id": "5c1860582722b75024b99449",
                    "code": "210321102",
                    "subdistrict": "新开河镇"
                },
                {
                    "_id": "5c1860582722b75024b99448",
                    "code": "210321103",
                    "subdistrict": "黄沙坨镇"
                },
                {
                    "_id": "5c1860582722b75024b99447",
                    "code": "210321104",
                    "subdistrict": "高力房镇"
                },
                {
                    "_id": "5c1860582722b75024b99446",
                    "code": "210321105",
                    "subdistrict": "桑林镇"
                },
                {
                    "_id": "5c1860582722b75024b99445",
                    "code": "210321106",
                    "subdistrict": "富家镇"
                },
                {
                    "_id": "5c1860582722b75024b99444",
                    "code": "210321107",
                    "subdistrict": "达牛镇"
                },
                {
                    "_id": "5c1860582722b75024b99443",
                    "code": "210321109",
                    "subdistrict": "台安县韭菜台镇"
                },
                {
                    "_id": "5c1860582722b75024b99442",
                    "code": "210321110",
                    "subdistrict": "新台镇"
                },
                {
                    "_id": "5c1860582722b75024b99441",
                    "code": "210321111",
                    "subdistrict": "桓洞镇"
                },
                {
                    "_id": "5c1860582722b75024b99440",
                    "code": "210321400",
                    "subdistrict": "新华农场"
                },
                {
                    "_id": "5c1860582722b75024b9943f",
                    "code": "210321401",
                    "subdistrict": "洪家农牧场"
                },
                {
                    "_id": "5c1860582722b75024b9943e",
                    "code": "210321402",
                    "subdistrict": "西平林场"
                }
            ]
        },
        {
            "_id": "5c1860582722b75024b99422",
            "code": "210323",
            "district": "岫岩满族自治县",
            "subdistricts": [
                {
                    "_id": "5c1860582722b75024b9943c",
                    "code": "210323001",
                    "subdistrict": "阜昌街道办事处"
                },
                {
                    "_id": "5c1860582722b75024b9943b",
                    "code": "210323002",
                    "subdistrict": "大宁街道办事处"
                },
                {
                    "_id": "5c1860582722b75024b9943a",
                    "code": "210323003",
                    "subdistrict": "兴隆街道办事处"
                },
                {
                    "_id": "5c1860582722b75024b99439",
                    "code": "210323004",
                    "subdistrict": "雅河街道办事处"
                },
                {
                    "_id": "5c1860582722b75024b99438",
                    "code": "210323005",
                    "subdistrict": "仙人咀街道办事处"
                },
                {
                    "_id": "5c1860582722b75024b99437",
                    "code": "210323101",
                    "subdistrict": "三家子镇"
                },
                {
                    "_id": "5c1860582722b75024b99436",
                    "code": "210323102",
                    "subdistrict": "石庙子镇"
                },
                {
                    "_id": "5c1860582722b75024b99435",
                    "code": "210323103",
                    "subdistrict": "黄花甸镇"
                },
                {
                    "_id": "5c1860582722b75024b99434",
                    "code": "210323104",
                    "subdistrict": "大营子镇"
                },
                {
                    "_id": "5c1860582722b75024b99433",
                    "code": "210323105",
                    "subdistrict": "苏子沟镇"
                },
                {
                    "_id": "5c1860582722b75024b99432",
                    "code": "210323106",
                    "subdistrict": "偏岭镇"
                },
                {
                    "_id": "5c1860582722b75024b99431",
                    "code": "210323107",
                    "subdistrict": "哈达碑镇"
                },
                {
                    "_id": "5c1860582722b75024b99430",
                    "code": "210323108",
                    "subdistrict": "新甸镇"
                },
                {
                    "_id": "5c1860582722b75024b9942f",
                    "code": "210323109",
                    "subdistrict": "洋河镇"
                },
                {
                    "_id": "5c1860582722b75024b9942e",
                    "code": "210323111",
                    "subdistrict": "杨家堡镇"
                },
                {
                    "_id": "5c1860582722b75024b9942d",
                    "code": "210323112",
                    "subdistrict": "清凉山镇"
                },
                {
                    "_id": "5c1860582722b75024b9942c",
                    "code": "210323113",
                    "subdistrict": "石灰窑镇"
                },
                {
                    "_id": "5c1860582722b75024b9942b",
                    "code": "210323114",
                    "subdistrict": "前营子镇"
                },
                {
                    "_id": "5c1860582722b75024b9942a",
                    "code": "210323115",
                    "subdistrict": "龙潭镇"
                },
                {
                    "_id": "5c1860582722b75024b99429",
                    "code": "210323116",
                    "subdistrict": "牧牛镇"
                },
                {
                    "_id": "5c1860582722b75024b99428",
                    "code": "210323117",
                    "subdistrict": "药山镇"
                },
                {
                    "_id": "5c1860582722b75024b99427",
                    "code": "210323118",
                    "subdistrict": "大房身镇"
                },
                {
                    "_id": "5c1860582722b75024b99426",
                    "code": "210323119",
                    "subdistrict": "朝阳镇"
                },
                {
                    "_id": "5c1860582722b75024b99425",
                    "code": "210323206",
                    "subdistrict": "红旗营子乡"
                },
                {
                    "_id": "5c1860582722b75024b99424",
                    "code": "210323211",
                    "subdistrict": "岭沟乡"
                },
                {
                    "_id": "5c1860582722b75024b99423",
                    "code": "210323212",
                    "subdistrict": "哨子河乡"
                }
            ]
        }
    ],
    "id": 51
}